{"bikes":[{"bike_id":"352897091527203","lat":38.8714083,"lon":-77.010725,"is_reserved":0,"is_disabled":0,"vehicle_type":"scooter"},{"bike_id":"352897091524564","lat":38.9042618,"lon":-77.0631024,"is_reserved":0,"is_disabled":0,"vehicle_type":"scooter"},{"bike_id":"352897091525165","lat":38.8922277,"lon":-77.0409687,"is_reserved":0,"is_disabled":0,"vehicle_type":"scooter"},{"bike_id":"352897091527146","lat":38.9110777,"lon":-77.0342242,"is_reserved":0,"is_disabled":0,"vehicle_type":"scooter"},{"bike_id":"352897091506223","lat":38.8973833,"lon":-77.02524,"is_reserved":0,"is_disabled":0,"vehicle_type":"scooter"},{"bike_id":"352897091525124","lat":38.9340183,"lon":-77.0861467,"is_reserved":0,"is_disabled":0,"vehicle_type":"scooter"},{"bike_id":"352897091526684","lat":38.8886679,"lon":-76.996797,"is_reserved":0,"is_disabled":0,"vehicle_type":"scooter"},{"bike_id":"352897091526320","lat":38.9085267,"lon":-77.0228983,"is_reserved":0,"is_disabled":0,"vehicle_type":"scooter"},{"bike_id":"352897091522147","lat":38.9262796,"lon":-77.0407807,"is_reserved":0,"is_disabled":0,"vehicle_type":"scooter"},{"bike_id":"352897091521081","lat":38.8640517,"lon":-76.97475,"is_reserved":0,"is_disabled":0,"vehicle_type":"scooter"},{"bike_id":"352897091523483","lat":38.9116333,"lon":-76.98859,"is_reserved":0,"is_disabled":0,"vehicle_type":"scooter"},{"bike_id":"352897091521107","lat":38.9351816,"lon":-77.0209988,"is_reserved":0,"is_disabled":0,"vehicle_type":"scooter"},{"bike_id":"352897091528409","lat":38.9298817,"lon":-77.0328433,"is_reserved":0,"is_disabled":0,"vehicle_type":"scooter"},{"bike_id":"352897091522162","lat":38.892375,"lon":-77.044695,"is_reserved":0,"is_disabled":0,"vehicle_type":"scooter"},{"bike_id":"352897091527328","lat":38.9044031,"lon":-77.0329782,"is_reserved":0,"is_disabled":0,"vehicle_type":"scooter"},{"bike_id":"352897091524184","lat":38.9461817,"lon":-77.0851333,"is_reserved":0,"is_disabled":0,"vehicle_type":"scooter"},{"bike_id":"352897091565807","lat":38.8956778,"lon":-77.0093983,"is_reserved":0,"is_disabled":0,"vehicle_type":"scooter"},{"bike_id":"352897091527427","lat":38.9038883,"lon":-77.06116,"is_reserved":0,"is_disabled":0,"vehicle_type":"scooter"},{"bike_id":"352897091528342","lat":38.9009906,"lon":-77.0502624,"is_reserved":0,"is_disabled":0,"vehicle_type":"scooter"},{"bike_id":"352897091526783","lat":38.9315512,"lon":-77.0563435,"is_reserved":0,"is_disabled":0,"vehicle_type":"scooter"},{"bike_id":"352897091525025","lat":38.881355,"lon":-76.9813133,"is_reserved":0,"is_disabled":0,"vehicle_type":"scooter"},{"bike_id":"352897091527385","lat":38.8772795,"lon":-77.0053588,"is_reserved":0,"is_disabled":0,"vehicle_type":"scooter"},{"bike_id":"352897091523848","lat":38.93736,"lon":-77.032644,"is_reserved":0,"is_disabled":0,"vehicle_type":"scooter"},{"bike_id":"352897091527526","lat":38.8853115,"lon":-77.0058465,"is_reserved":0,"is_disabled":0,"vehicle_type":"scooter"},{"bike_id":"352897091528227","lat":38.9101874,"lon":-77.0385425,"is_reserved":0,"is_disabled":0,"vehicle_type":"scooter"},{"bike_id":"352897091527369","lat":38.9090265,"lon":-77.0053604,"is_reserved":0,"is_disabled":0,"vehicle_type":"scooter"},{"bike_id":"352897091525108","lat":38.8988217,"lon":-77.015625,"is_reserved":0,"is_disabled":0,"vehicle_type":"scooter"},{"bike_id":"352897091527260","lat":38.9036617,"lon":-77.0397983,"is_reserved":0,"is_disabled":0,"vehicle_type":"scooter"},{"bike_id":"352897091538945","lat":38.8966036,"lon":-77.03317,"is_reserved":0,"is_disabled":0,"vehicle_type":"scooter"},{"bike_id":"352897091565625","lat":38.8934784,"lon":-77.0401278,"is_reserved":0,"is_disabled":0,"vehicle_type":"scooter"},{"bike_id":"352897091525009","lat":38.9064501,"lon":-77.0250554,"is_reserved":0,"is_disabled":0,"vehicle_type":"scooter"},{"bike_id":"352897091490568","lat":38.9306399,"lon":-77.0319643,"is_reserved":0,"is_disabled":0,"vehicle_type":"scooter"},{"bike_id":"352897091401961","lat":38.9054367,"lon":-77.0418967,"is_reserved":0,"is_disabled":0,"vehicle_type":"scooter"},{"bike_id":"352897091288509","lat":38.9234617,"lon":-77.04344,"is_reserved":0,"is_disabled":0,"vehicle_type":"scooter"},{"bike_id":"352897091412844","lat":38.9151017,"lon":-77.0672383,"is_reserved":0,"is_disabled":0,"vehicle_type":"scooter"},{"bike_id":"352897091642622","lat":38.9038417,"lon":-77.0532383,"is_reserved":0,"is_disabled":0,"vehicle_type":"scooter"},{"bike_id":"352897091642507","lat":38.9259867,"lon":-77.0353883,"is_reserved":0,"is_disabled":0,"vehicle_type":"scooter"},{"bike_id":"352897091370521","lat":38.8740933,"lon":-76.9711883,"is_reserved":0,"is_disabled":0,"vehicle_type":"scooter"},{"bike_id":"352897091416845","lat":38.9012447,"lon":-77.0497901,"is_reserved":0,"is_disabled":0,"vehicle_type":"scooter"},{"bike_id":"352897091362387","lat":38.9067954,"lon":-77.0622291,"is_reserved":0,"is_disabled":0,"vehicle_type":"scooter"},{"bike_id":"352897091456205","lat":38.874897,"lon":-77.0006146,"is_reserved":0,"is_disabled":0,"vehicle_type":"scooter"},{"bike_id":"352897091438641","lat":38.8997722,"lon":-77.0216569,"is_reserved":0,"is_disabled":0,"vehicle_type":"scooter"},{"bike_id":"352897091308620","lat":38.9053967,"lon":-77.0029217,"is_reserved":0,"is_disabled":0,"vehicle_type":"scooter"},{"bike_id":"352897091362486","lat":38.9253994,"lon":-77.0338669,"is_reserved":0,"is_disabled":0,"vehicle_type":"scooter"},{"bike_id":"352897091316904","lat":38.915025,"lon":-77.0448433,"is_reserved":0,"is_disabled":0,"vehicle_type":"scooter"},{"bike_id":"352897091412547","lat":38.9034517,"lon":-77.0089183,"is_reserved":0,"is_disabled":0,"vehicle_type":"scooter"},{"bike_id":"352897091312309","lat":38.9128069,"lon":-77.0318722,"is_reserved":0,"is_disabled":0,"vehicle_type":"scooter"},{"bike_id":"352897091413388","lat":38.91037,"lon":-77.06468,"is_reserved":0,"is_disabled":0,"vehicle_type":"scooter"},{"bike_id":"352897091573884","lat":38.9209939,"lon":-77.0320117,"is_reserved":0,"is_disabled":0,"vehicle_type":"scooter"},{"bike_id":"352897091367808","lat":38.87496,"lon":-76.9979183,"is_reserved":0,"is_disabled":0,"vehicle_type":"scooter"},{"bike_id":"352897091445323","lat":38.9181762,"lon":-77.0316001,"is_reserved":0,"is_disabled":0,"vehicle_type":"scooter"},{"bike_id":"352897091399868","lat":38.9164572,"lon":-77.0464173,"is_reserved":0,"is_disabled":0,"vehicle_type":"scooter"},{"bike_id":"352897091276884","lat":38.8999688,"lon":-77.0260038,"is_reserved":0,"is_disabled":0,"vehicle_type":"scooter"},{"bike_id":"352897091403223","lat":38.8970874,"lon":-77.0227284,"is_reserved":0,"is_disabled":0,"vehicle_type":"scooter"},{"bike_id":"352897091271984","lat":38.9087367,"lon":-77.0346383,"is_reserved":0,"is_disabled":0,"vehicle_type":"scooter"},{"bike_id":"352897091326929","lat":38.9306633,"lon":-77.038125,"is_reserved":0,"is_disabled":0,"vehicle_type":"scooter"},{"bike_id":"352897091360720","lat":38.8765682,"lon":-77.0073245,"is_reserved":0,"is_disabled":0,"vehicle_type":"scooter"},{"bike_id":"352897091552805","lat":38.8774833,"lon":-77.0035467,"is_reserved":0,"is_disabled":0,"vehicle_type":"scooter"},{"bike_id":"352897091287808","lat":38.9055225,"lon":-77.0296975,"is_reserved":0,"is_disabled":0,"vehicle_type":"scooter"},{"bike_id":"352897091295744","lat":38.8971633,"lon":-77.0480934,"is_reserved":0,"is_disabled":0,"vehicle_type":"scooter"},{"bike_id":"352897091415441","lat":38.8741367,"lon":-76.9711833,"is_reserved":0,"is_disabled":0,"vehicle_type":"scooter"},{"bike_id":"352897091393986","lat":38.8997764,"lon":-77.0463658,"is_reserved":0,"is_disabled":0,"vehicle_type":"scooter"},{"bike_id":"352897091567084","lat":38.918114,"lon":-77.0344399,"is_reserved":0,"is_disabled":0,"vehicle_type":"scooter"},{"bike_id":"352897091452246","lat":38.9093775,"lon":-77.0408926,"is_reserved":0,"is_disabled":0,"vehicle_type":"scooter"},{"bike_id":"352897091384522","lat":38.9038815,"lon":-77.0183824,"is_reserved":0,"is_disabled":0,"vehicle_type":"scooter"},{"bike_id":"352897091361207","lat":38.9025772,"lon":-77.0034462,"is_reserved":0,"is_disabled":0,"vehicle_type":"scooter"},{"bike_id":"352897091479843","lat":38.8666034,"lon":-76.9888534,"is_reserved":0,"is_disabled":0,"vehicle_type":"scooter"},{"bike_id":"352897091407026","lat":38.9032217,"lon":-77.0118567,"is_reserved":0,"is_disabled":0,"vehicle_type":"scooter"},{"bike_id":"352897091375447","lat":38.879775,"lon":-77.0154583,"is_reserved":0,"is_disabled":0,"vehicle_type":"scooter"},{"bike_id":"352897091300767","lat":38.8741234,"lon":-76.9711175,"is_reserved":0,"is_disabled":0,"vehicle_type":"scooter"},{"bike_id":"352897091370745","lat":38.915485,"lon":-77.041745,"is_reserved":0,"is_disabled":0,"vehicle_type":"scooter"},{"bike_id":"352897091399009","lat":38.9334817,"lon":-77.0726317,"is_reserved":0,"is_disabled":0,"vehicle_type":"scooter"},{"bike_id":"352897091456841","lat":38.9005787,"lon":-77.001941,"is_reserved":0,"is_disabled":0,"vehicle_type":"scooter"},{"bike_id":"352897091563240","lat":38.88641,"lon":-77.0009651,"is_reserved":0,"is_disabled":0,"vehicle_type":"scooter"},{"bike_id":"352897091303225","lat":38.8748068,"lon":-77.0075823,"is_reserved":0,"is_disabled":0,"vehicle_type":"scooter"},{"bike_id":"352897091394661","lat":38.9169033,"lon":-77.0411867,"is_reserved":0,"is_disabled":0,"vehicle_type":"scooter"},{"bike_id":"352897091353923","lat":38.9007583,"lon":-77.049245,"is_reserved":0,"is_disabled":0,"vehicle_type":"scooter"},{"bike_id":"352897091516446","lat":38.9022633,"lon":-77.061097,"is_reserved":0,"is_disabled":0,"vehicle_type":"scooter"},{"bike_id":"352897091650625","lat":38.9135398,"lon":-77.0442748,"is_reserved":0,"is_disabled":0,"vehicle_type":"scooter"},{"bike_id":"352897091304249","lat":38.9130094,"lon":-77.031702,"is_reserved":0,"is_disabled":0,"vehicle_type":"scooter"},{"bike_id":"352897091434103","lat":38.9376267,"lon":-77.0226067,"is_reserved":0,"is_disabled":0,"vehicle_type":"scooter"},{"bike_id":"352897091283724","lat":38.9036359,"lon":-77.0418552,"is_reserved":0,"is_disabled":0,"vehicle_type":"scooter"},{"bike_id":"352897091421969","lat":38.886248,"lon":-77.0165977,"is_reserved":0,"is_disabled":0,"vehicle_type":"scooter"},{"bike_id":"352897091466782","lat":38.8970883,"lon":-77.0226933,"is_reserved":0,"is_disabled":0,"vehicle_type":"scooter"},{"bike_id":"352897091529969","lat":38.9069783,"lon":-77.0239346,"is_reserved":0,"is_disabled":0,"vehicle_type":"scooter"},{"bike_id":"352897091344047","lat":38.90375,"lon":-77.0202183,"is_reserved":0,"is_disabled":0,"vehicle_type":"scooter"},{"bike_id":"352897091536444","lat":38.9206305,"lon":-77.0338558,"is_reserved":0,"is_disabled":0,"vehicle_type":"scooter"},{"bike_id":"352897091279847","lat":38.924455,"lon":-77.0335783,"is_reserved":0,"is_disabled":0,"vehicle_type":"scooter"},{"bike_id":"352897091357023","lat":38.8715808,"lon":-77.0058578,"is_reserved":0,"is_disabled":0,"vehicle_type":"scooter"},{"bike_id":"352897091265382","lat":38.9070815,"lon":-77.0478483,"is_reserved":0,"is_disabled":0,"vehicle_type":"scooter"},{"bike_id":"352897091463102","lat":38.9176694,"lon":-77.0221938,"is_reserved":0,"is_disabled":0,"vehicle_type":"scooter"},{"bike_id":"352897091328503","lat":38.9153183,"lon":-77.0379567,"is_reserved":0,"is_disabled":0,"vehicle_type":"scooter"},{"bike_id":"352897091403462","lat":38.9168917,"lon":-77.0347367,"is_reserved":0,"is_disabled":0,"vehicle_type":"scooter"},{"bike_id":"352897091425002","lat":38.9148574,"lon":-77.0322059,"is_reserved":0,"is_disabled":0,"vehicle_type":"scooter"},{"bike_id":"352897091420300","lat":38.908945,"lon":-77.0434164,"is_reserved":0,"is_disabled":0,"vehicle_type":"scooter"},{"bike_id":"352897091397243","lat":38.9135467,"lon":-77.0442983,"is_reserved":0,"is_disabled":0,"vehicle_type":"scooter"},{"bike_id":"352897091267883","lat":38.8765803,"lon":-77.0005572,"is_reserved":0,"is_disabled":0,"vehicle_type":"scooter"},{"bike_id":"352897091298821","lat":38.8764083,"lon":-77.000445,"is_reserved":0,"is_disabled":0,"vehicle_type":"scooter"},{"bike_id":"352897091295983","lat":38.9051638,"lon":-77.057662,"is_reserved":0,"is_disabled":0,"vehicle_type":"scooter"},{"bike_id":"352897091524549","lat":38.9291847,"lon":-77.0326413,"is_reserved":0,"is_disabled":0,"vehicle_type":"scooter"},{"bike_id":"352897091466402","lat":38.9001483,"lon":-76.9985317,"is_reserved":0,"is_disabled":0,"vehicle_type":"scooter"},{"bike_id":"352897091313000","lat":38.904392,"lon":-77.0405348,"is_reserved":0,"is_disabled":0,"vehicle_type":"scooter"},{"bike_id":"352897091425986","lat":38.91727,"lon":-77.029735,"is_reserved":0,"is_disabled":0,"vehicle_type":"scooter"},{"bike_id":"352897091442122","lat":38.9037614,"lon":-77.0502961,"is_reserved":0,"is_disabled":0,"vehicle_type":"scooter"},{"bike_id":"352897091380389","lat":38.9360233,"lon":-77.0586483,"is_reserved":0,"is_disabled":0,"vehicle_type":"scooter"},{"bike_id":"352897091462906","lat":38.892415,"lon":-77.032315,"is_reserved":0,"is_disabled":0,"vehicle_type":"scooter"},{"bike_id":"352897091515240","lat":38.90884,"lon":-77.0433137,"is_reserved":0,"is_disabled":0,"vehicle_type":"scooter"},{"bike_id":"352897091286461","lat":38.8758334,"lon":-77.007555,"is_reserved":0,"is_disabled":0,"vehicle_type":"scooter"},{"bike_id":"352897091411002","lat":38.899895,"lon":-77.0207167,"is_reserved":0,"is_disabled":0,"vehicle_type":"scooter"},{"bike_id":"352897091463227","lat":38.9142233,"lon":-77.0321083,"is_reserved":0,"is_disabled":0,"vehicle_type":"scooter"},{"bike_id":"352897091344344","lat":38.9046415,"lon":-77.0170679,"is_reserved":0,"is_disabled":0,"vehicle_type":"scooter"},{"bike_id":"352897091566102","lat":38.9150749,"lon":-77.0685476,"is_reserved":0,"is_disabled":0,"vehicle_type":"scooter"},{"bike_id":"352897091302425","lat":38.917085,"lon":-77.04126,"is_reserved":0,"is_disabled":0,"vehicle_type":"scooter"},{"bike_id":"352897091359722","lat":38.8666467,"lon":-76.9887633,"is_reserved":0,"is_disabled":0,"vehicle_type":"scooter"},{"bike_id":"352897091298060","lat":38.92804,"lon":-77.03078,"is_reserved":0,"is_disabled":0,"vehicle_type":"scooter"},{"bike_id":"352897091347180","lat":38.9090913,"lon":-77.0451685,"is_reserved":0,"is_disabled":0,"vehicle_type":"scooter"},{"bike_id":"352897091636541","lat":38.9233773,"lon":-77.0433839,"is_reserved":0,"is_disabled":0,"vehicle_type":"scooter"},{"bike_id":"352897091542160","lat":38.8977817,"lon":-77.04819,"is_reserved":0,"is_disabled":0,"vehicle_type":"scooter"},{"bike_id":"352897091529225","lat":38.89921,"lon":-77.0323483,"is_reserved":0,"is_disabled":0,"vehicle_type":"scooter"},{"bike_id":"352897091338700","lat":38.905325,"lon":-77.0270417,"is_reserved":0,"is_disabled":0,"vehicle_type":"scooter"},{"bike_id":"352897091478704","lat":38.916265,"lon":-77.0320123,"is_reserved":0,"is_disabled":0,"vehicle_type":"scooter"},{"bike_id":"352897091352842","lat":38.916885,"lon":-77.0386966,"is_reserved":0,"is_disabled":0,"vehicle_type":"scooter"},{"bike_id":"352897091396427","lat":38.9235233,"lon":-77.043495,"is_reserved":0,"is_disabled":0,"vehicle_type":"scooter"},{"bike_id":"352897091348923","lat":38.8958847,"lon":-77.0309545,"is_reserved":0,"is_disabled":0,"vehicle_type":"scooter"},{"bike_id":"352897091413727","lat":38.9077249,"lon":-77.0356558,"is_reserved":0,"is_disabled":0,"vehicle_type":"scooter"},{"bike_id":"352897091399686","lat":38.9067779,"lon":-77.0637369,"is_reserved":0,"is_disabled":0,"vehicle_type":"scooter"},{"bike_id":"352897091648421","lat":38.9020387,"lon":-77.0262857,"is_reserved":0,"is_disabled":0,"vehicle_type":"scooter"},{"bike_id":"352897091457005","lat":38.8749517,"lon":-76.99998,"is_reserved":0,"is_disabled":0,"vehicle_type":"scooter"},{"bike_id":"352897091308448","lat":38.909628,"lon":-77.0454991,"is_reserved":0,"is_disabled":0,"vehicle_type":"scooter"},{"bike_id":"352897091290869","lat":38.8956583,"lon":-77.0111383,"is_reserved":0,"is_disabled":0,"vehicle_type":"scooter"},{"bike_id":"352897091641301","lat":38.9051874,"lon":-77.0576481,"is_reserved":0,"is_disabled":0,"vehicle_type":"scooter"},{"bike_id":"352897091349509","lat":38.8580696,"lon":-76.9866398,"is_reserved":0,"is_disabled":0,"vehicle_type":"scooter"},{"bike_id":"352897091401805","lat":38.9122983,"lon":-77.013897,"is_reserved":0,"is_disabled":0,"vehicle_type":"scooter"},{"bike_id":"352897091317423","lat":38.903845,"lon":-77.0400767,"is_reserved":0,"is_disabled":0,"vehicle_type":"scooter"},{"bike_id":"352897091423726","lat":38.902893,"lon":-77.0226229,"is_reserved":0,"is_disabled":0,"vehicle_type":"scooter"},{"bike_id":"352897091380066","lat":38.9196648,"lon":-77.0248688,"is_reserved":0,"is_disabled":0,"vehicle_type":"scooter"},{"bike_id":"352897091343841","lat":38.9049483,"lon":-77.0600383,"is_reserved":0,"is_disabled":0,"vehicle_type":"scooter"},{"bike_id":"352897091465586","lat":38.903845,"lon":-77.0533033,"is_reserved":0,"is_disabled":0,"vehicle_type":"scooter"},{"bike_id":"352897091269202","lat":38.8973345,"lon":-77.0484722,"is_reserved":0,"is_disabled":0,"vehicle_type":"scooter"},{"bike_id":"352897091353808","lat":38.9174413,"lon":-77.069159,"is_reserved":0,"is_disabled":0,"vehicle_type":"scooter"},{"bike_id":"352897091564644","lat":38.9201731,"lon":-77.0440138,"is_reserved":0,"is_disabled":0,"vehicle_type":"scooter"},{"bike_id":"352897091643703","lat":38.8992678,"lon":-77.0323799,"is_reserved":0,"is_disabled":0,"vehicle_type":"scooter"},{"bike_id":"352897091499288","lat":38.8751083,"lon":-77.0007817,"is_reserved":0,"is_disabled":0,"vehicle_type":"scooter"},{"bike_id":"352897091353287","lat":38.9082167,"lon":-77.0219717,"is_reserved":0,"is_disabled":0,"vehicle_type":"scooter"},{"bike_id":"352897091483282","lat":38.9151379,"lon":-77.0321917,"is_reserved":0,"is_disabled":0,"vehicle_type":"scooter"},{"bike_id":"352897091332067","lat":38.9360664,"lon":-77.058612,"is_reserved":0,"is_disabled":0,"vehicle_type":"scooter"},{"bike_id":"352897091368145","lat":38.8927017,"lon":-76.9513517,"is_reserved":0,"is_disabled":0,"vehicle_type":"scooter"},{"bike_id":"352897091376429","lat":38.90683,"lon":-77.0432133,"is_reserved":0,"is_disabled":0,"vehicle_type":"scooter"},{"bike_id":"352897091356181","lat":38.91328,"lon":-77.05206,"is_reserved":0,"is_disabled":0,"vehicle_type":"scooter"},{"bike_id":"352897091410269","lat":38.9160216,"lon":-76.9736895,"is_reserved":0,"is_disabled":0,"vehicle_type":"scooter"},{"bike_id":"352897091468440","lat":38.9247151,"lon":-77.0393204,"is_reserved":0,"is_disabled":0,"vehicle_type":"scooter"},{"bike_id":"352897091282288","lat":38.9062971,"lon":-77.0571728,"is_reserved":0,"is_disabled":0,"vehicle_type":"scooter"},{"bike_id":"352897091651847","lat":38.8758367,"lon":-77.23434,"is_reserved":0,"is_disabled":0,"vehicle_type":"scooter"},{"bike_id":"352897091569122","lat":38.9079035,"lon":-77.0580064,"is_reserved":0,"is_disabled":0,"vehicle_type":"scooter"},{"bike_id":"352897091567860","lat":38.9070099,"lon":-77.0241346,"is_reserved":0,"is_disabled":0,"vehicle_type":"scooter"},{"bike_id":"352897091456866","lat":38.92442,"lon":-77.0403462,"is_reserved":0,"is_disabled":0,"vehicle_type":"scooter"},{"bike_id":"352897091308125","lat":38.9015547,"lon":-77.0499785,"is_reserved":0,"is_disabled":0,"vehicle_type":"scooter"},{"bike_id":"352897091292428","lat":38.902445,"lon":-77.0188133,"is_reserved":0,"is_disabled":0,"vehicle_type":"scooter"},{"bike_id":"352897091411069","lat":38.9103444,"lon":-77.0128321,"is_reserved":0,"is_disabled":0,"vehicle_type":"scooter"},{"bike_id":"352897091516040","lat":38.9248699,"lon":-77.0393837,"is_reserved":0,"is_disabled":0,"vehicle_type":"scooter"},{"bike_id":"352897091363385","lat":38.918039,"lon":-77.039099,"is_reserved":0,"is_disabled":0,"vehicle_type":"scooter"},{"bike_id":"352897091415987","lat":38.9052003,"lon":-77.0577137,"is_reserved":0,"is_disabled":0,"vehicle_type":"scooter"},{"bike_id":"352897091267768","lat":38.8765283,"lon":-77.0041667,"is_reserved":0,"is_disabled":0,"vehicle_type":"scooter"},{"bike_id":"352897091394224","lat":38.8999002,"lon":-77.0198202,"is_reserved":0,"is_disabled":0,"vehicle_type":"scooter"},{"bike_id":"352897091638323","lat":38.9056278,"lon":-77.0129215,"is_reserved":0,"is_disabled":0,"vehicle_type":"scooter"},{"bike_id":"352897091567928","lat":38.9054681,"lon":-77.0418852,"is_reserved":0,"is_disabled":0,"vehicle_type":"scooter"},{"bike_id":"352897091368160","lat":38.90245,"lon":-77.0385067,"is_reserved":0,"is_disabled":0,"vehicle_type":"scooter"},{"bike_id":"352897091375926","lat":38.8975516,"lon":-77.0480417,"is_reserved":0,"is_disabled":0,"vehicle_type":"scooter"},{"bike_id":"352897091343965","lat":38.9141681,"lon":-77.0355751,"is_reserved":0,"is_disabled":0,"vehicle_type":"scooter"},{"bike_id":"352897091329709","lat":38.9127733,"lon":-77.0312617,"is_reserved":0,"is_disabled":0,"vehicle_type":"scooter"},{"bike_id":"352897091409584","lat":38.8973183,"lon":-77.0433033,"is_reserved":0,"is_disabled":0,"vehicle_type":"scooter"},{"bike_id":"352897091476302","lat":38.8704558,"lon":-76.9822724,"is_reserved":0,"is_disabled":0,"vehicle_type":"scooter"},{"bike_id":"352897091384126","lat":38.9112833,"lon":-77.0380967,"is_reserved":0,"is_disabled":0,"vehicle_type":"scooter"},{"bike_id":"352897091272941","lat":38.901355,"lon":-76.9961883,"is_reserved":0,"is_disabled":0,"vehicle_type":"scooter"},{"bike_id":"352897091429103","lat":38.9177587,"lon":-77.0356911,"is_reserved":0,"is_disabled":0,"vehicle_type":"scooter"},{"bike_id":"352897091370604","lat":38.9071541,"lon":-77.0521456,"is_reserved":0,"is_disabled":0,"vehicle_type":"scooter"},{"bike_id":"352897091399546","lat":38.9196883,"lon":-77.0418433,"is_reserved":0,"is_disabled":0,"vehicle_type":"scooter"},{"bike_id":"352897091377864","lat":38.9057433,"lon":-77.02174,"is_reserved":0,"is_disabled":0,"vehicle_type":"scooter"},{"bike_id":"352897091362247","lat":38.908475,"lon":-77.0319533,"is_reserved":0,"is_disabled":0,"vehicle_type":"scooter"},{"bike_id":"352897091639784","lat":38.9163291,"lon":-77.0320959,"is_reserved":0,"is_disabled":0,"vehicle_type":"scooter"},{"bike_id":"352897091332687","lat":38.9244303,"lon":-77.0403151,"is_reserved":0,"is_disabled":0,"vehicle_type":"scooter"},{"bike_id":"352897091478605","lat":38.8952834,"lon":-77.0133852,"is_reserved":0,"is_disabled":0,"vehicle_type":"scooter"},{"bike_id":"352897091515208","lat":38.9044089,"lon":-77.0170197,"is_reserved":0,"is_disabled":0,"vehicle_type":"scooter"},{"bike_id":"352897091488000","lat":38.9085216,"lon":-76.9981403,"is_reserved":0,"is_disabled":0,"vehicle_type":"scooter"},{"bike_id":"352897091331986","lat":38.9037886,"lon":-76.9962799,"is_reserved":0,"is_disabled":0,"vehicle_type":"scooter"},{"bike_id":"352897091476963","lat":38.8872782,"lon":-77.0145035,"is_reserved":0,"is_disabled":0,"vehicle_type":"scooter"},{"bike_id":"352897091540487","lat":38.9003467,"lon":-77.0003917,"is_reserved":0,"is_disabled":0,"vehicle_type":"scooter"},{"bike_id":"352897091278849","lat":38.9048733,"lon":-77.0487383,"is_reserved":0,"is_disabled":0,"vehicle_type":"scooter"},{"bike_id":"352897091367907","lat":38.9270332,"lon":-77.0508234,"is_reserved":0,"is_disabled":0,"vehicle_type":"scooter"},{"bike_id":"352897091456668","lat":38.9165044,"lon":-77.0290876,"is_reserved":0,"is_disabled":0,"vehicle_type":"scooter"},{"bike_id":"352897091287246","lat":38.9032009,"lon":-77.0539284,"is_reserved":0,"is_disabled":0,"vehicle_type":"scooter"},{"bike_id":"352897091478167","lat":38.9289701,"lon":-77.0326169,"is_reserved":0,"is_disabled":0,"vehicle_type":"scooter"},{"bike_id":"352897091352149","lat":38.9234933,"lon":-77.0389733,"is_reserved":0,"is_disabled":0,"vehicle_type":"scooter"},{"bike_id":"352897091433063","lat":38.8656869,"lon":-76.9893865,"is_reserved":0,"is_disabled":0,"vehicle_type":"scooter"},{"bike_id":"352897091286768","lat":38.9301521,"lon":-77.0368868,"is_reserved":0,"is_disabled":0,"vehicle_type":"scooter"},{"bike_id":"352897091394802","lat":38.9224833,"lon":-77.0428798,"is_reserved":0,"is_disabled":0,"vehicle_type":"scooter"},{"bike_id":"352897091640527","lat":38.9028017,"lon":-77.0321986,"is_reserved":0,"is_disabled":0,"vehicle_type":"scooter"},{"bike_id":"352897091446180","lat":38.92383,"lon":-77.0274,"is_reserved":0,"is_disabled":0,"vehicle_type":"scooter"},{"bike_id":"352897091350044","lat":38.9227987,"lon":-77.0341139,"is_reserved":0,"is_disabled":0,"vehicle_type":"scooter"},{"bike_id":"352897091482847","lat":38.9087833,"lon":-77.0347467,"is_reserved":0,"is_disabled":0,"vehicle_type":"scooter"},{"bike_id":"352897091264344","lat":38.9308533,"lon":-77.03158,"is_reserved":0,"is_disabled":0,"vehicle_type":"scooter"},{"bike_id":"352897091466527","lat":38.8803967,"lon":-77.00501,"is_reserved":0,"is_disabled":0,"vehicle_type":"scooter"},{"bike_id":"352897091456148","lat":38.9012743,"lon":-77.0500981,"is_reserved":0,"is_disabled":0,"vehicle_type":"scooter"},{"bike_id":"352897091493000","lat":38.9253557,"lon":-77.0326058,"is_reserved":0,"is_disabled":0,"vehicle_type":"scooter"},{"bike_id":"352897091652340","lat":38.8919498,"lon":-77.046204,"is_reserved":0,"is_disabled":0,"vehicle_type":"scooter"},{"bike_id":"352897091413602","lat":38.876475,"lon":-77.000375,"is_reserved":0,"is_disabled":0,"vehicle_type":"scooter"},{"bike_id":"352897091363104","lat":38.8924084,"lon":-77.0260707,"is_reserved":0,"is_disabled":0,"vehicle_type":"scooter"},{"bike_id":"352897091361942","lat":38.9128183,"lon":-77.0321533,"is_reserved":0,"is_disabled":0,"vehicle_type":"scooter"},{"bike_id":"352897091445828","lat":38.9078191,"lon":-77.0434546,"is_reserved":0,"is_disabled":0,"vehicle_type":"scooter"},{"bike_id":"352897091488026","lat":38.9032517,"lon":-77.018885,"is_reserved":0,"is_disabled":0,"vehicle_type":"scooter"},{"bike_id":"352897091298243","lat":38.9244183,"lon":-77.0402883,"is_reserved":0,"is_disabled":0,"vehicle_type":"scooter"},{"bike_id":"352897091307168","lat":38.87922,"lon":-77.0072951,"is_reserved":0,"is_disabled":0,"vehicle_type":"scooter"},{"bike_id":"352897091533540","lat":38.9110146,"lon":-77.0426859,"is_reserved":0,"is_disabled":0,"vehicle_type":"scooter"},{"bike_id":"352897091492044","lat":38.91876,"lon":-77.0448433,"is_reserved":0,"is_disabled":0,"vehicle_type":"scooter"},{"bike_id":"352897091365364","lat":38.9038281,"lon":-77.0449094,"is_reserved":0,"is_disabled":0,"vehicle_type":"scooter"},{"bike_id":"352897091561921","lat":38.903422,"lon":-76.9984696,"is_reserved":0,"is_disabled":0,"vehicle_type":"scooter"},{"bike_id":"352897091314644","lat":38.9056957,"lon":-77.0306998,"is_reserved":0,"is_disabled":0,"vehicle_type":"scooter"},{"bike_id":"352897091383680","lat":38.9050929,"lon":-77.0176341,"is_reserved":0,"is_disabled":0,"vehicle_type":"scooter"},{"bike_id":"352897091394901","lat":38.90364,"lon":-77.041875,"is_reserved":0,"is_disabled":0,"vehicle_type":"scooter"},{"bike_id":"352897091280126","lat":38.9332616,"lon":-77.0569783,"is_reserved":0,"is_disabled":0,"vehicle_type":"scooter"},{"bike_id":"352897091437361","lat":38.9149903,"lon":-77.0674379,"is_reserved":0,"is_disabled":0,"vehicle_type":"scooter"},{"bike_id":"352897091416209","lat":38.9007784,"lon":-77.0531748,"is_reserved":0,"is_disabled":0,"vehicle_type":"scooter"},{"bike_id":"352897091471105","lat":38.9235407,"lon":-77.0402143,"is_reserved":0,"is_disabled":0,"vehicle_type":"scooter"},{"bike_id":"352897091467186","lat":38.9014711,"lon":-77.050077,"is_reserved":0,"is_disabled":0,"vehicle_type":"scooter"},{"bike_id":"352897091422843","lat":38.9024456,"lon":-77.0175605,"is_reserved":0,"is_disabled":0,"vehicle_type":"scooter"},{"bike_id":"352897091275084","lat":38.903725,"lon":-77.0499733,"is_reserved":0,"is_disabled":0,"vehicle_type":"scooter"},{"bike_id":"352897091307283","lat":38.9161686,"lon":-76.9830671,"is_reserved":0,"is_disabled":0,"vehicle_type":"scooter"},{"bike_id":"352897091368483","lat":38.8760675,"lon":-77.0041107,"is_reserved":0,"is_disabled":0,"vehicle_type":"scooter"},{"bike_id":"352897091299142","lat":38.9204983,"lon":-77.0358433,"is_reserved":0,"is_disabled":0,"vehicle_type":"scooter"},{"bike_id":"352897091306087","lat":38.8983357,"lon":-77.0264728,"is_reserved":0,"is_disabled":0,"vehicle_type":"scooter"},{"bike_id":"352897091346141","lat":38.931929,"lon":-77.0252698,"is_reserved":0,"is_disabled":0,"vehicle_type":"scooter"},{"bike_id":"352897091468309","lat":38.9038173,"lon":-77.0466285,"is_reserved":0,"is_disabled":0,"vehicle_type":"scooter"},{"bike_id":"352897091398761","lat":38.914785,"lon":-77.0417017,"is_reserved":0,"is_disabled":0,"vehicle_type":"scooter"},{"bike_id":"352897091363427","lat":38.9025808,"lon":-77.0155563,"is_reserved":0,"is_disabled":0,"vehicle_type":"scooter"},{"bike_id":"352897091414782","lat":38.905485,"lon":-77.0435918,"is_reserved":0,"is_disabled":0,"vehicle_type":"scooter"},{"bike_id":"352897091364441","lat":38.9073146,"lon":-77.0481047,"is_reserved":0,"is_disabled":0,"vehicle_type":"scooter"},{"bike_id":"352897091476146","lat":38.8971877,"lon":-77.0278015,"is_reserved":0,"is_disabled":0,"vehicle_type":"scooter"},{"bike_id":"352897091374903","lat":38.9075817,"lon":-77.0768893,"is_reserved":0,"is_disabled":0,"vehicle_type":"scooter"},{"bike_id":"352897091323405","lat":38.8956467,"lon":-77.029275,"is_reserved":0,"is_disabled":0,"vehicle_type":"scooter"},{"bike_id":"352897091638240","lat":38.9139856,"lon":-77.0322814,"is_reserved":0,"is_disabled":0,"vehicle_type":"scooter"},{"bike_id":"352897091301724","lat":38.91825,"lon":-77.0392017,"is_reserved":0,"is_disabled":0,"vehicle_type":"scooter"},{"bike_id":"352897091564768","lat":38.9056026,"lon":-77.0294704,"is_reserved":0,"is_disabled":0,"vehicle_type":"scooter"},{"bike_id":"352897091449564","lat":38.9300883,"lon":-77.0346978,"is_reserved":0,"is_disabled":0,"vehicle_type":"scooter"},{"bike_id":"352897091457120","lat":38.8997973,"lon":-77.0216783,"is_reserved":0,"is_disabled":0,"vehicle_type":"scooter"},{"bike_id":"352897091384506","lat":38.9129467,"lon":-77.0321033,"is_reserved":0,"is_disabled":0,"vehicle_type":"scooter"},{"bike_id":"352897091516701","lat":38.9036567,"lon":-77.0179817,"is_reserved":0,"is_disabled":0,"vehicle_type":"scooter"},{"bike_id":"352897091267644","lat":38.8775067,"lon":-76.9970967,"is_reserved":0,"is_disabled":0,"vehicle_type":"scooter"},{"bike_id":"352897091432628","lat":38.9336376,"lon":-77.072518,"is_reserved":0,"is_disabled":0,"vehicle_type":"scooter"},{"bike_id":"352897091453301","lat":38.897355,"lon":-76.9472167,"is_reserved":0,"is_disabled":0,"vehicle_type":"scooter"},{"bike_id":"352897091561442","lat":38.8754265,"lon":-77.2346501,"is_reserved":0,"is_disabled":0,"vehicle_type":"scooter"},{"bike_id":"352897091214729","lat":38.9073617,"lon":-77.0422183,"is_reserved":0,"is_disabled":0,"vehicle_type":"scooter"},{"bike_id":"352897091412141","lat":38.90489,"lon":-77.0403033,"is_reserved":0,"is_disabled":0,"vehicle_type":"scooter"},{"bike_id":"352897091429384","lat":38.9046687,"lon":-77.0076265,"is_reserved":0,"is_disabled":0,"vehicle_type":"scooter"},{"bike_id":"352897091367543","lat":38.9239383,"lon":-77.0273233,"is_reserved":0,"is_disabled":0,"vehicle_type":"scooter"},{"bike_id":"352897091647167","lat":38.9348366,"lon":-77.0209757,"is_reserved":0,"is_disabled":0,"vehicle_type":"scooter"},{"bike_id":"352897091292303","lat":38.9291417,"lon":-77.032915,"is_reserved":0,"is_disabled":0,"vehicle_type":"scooter"},{"bike_id":"352897091292261","lat":38.906565,"lon":-77.0384833,"is_reserved":0,"is_disabled":0,"vehicle_type":"scooter"},{"bike_id":"352897091461700","lat":38.8939418,"lon":-77.0300752,"is_reserved":0,"is_disabled":0,"vehicle_type":"scooter"},{"bike_id":"352897091337181","lat":38.893751,"lon":-76.9500215,"is_reserved":0,"is_disabled":0,"vehicle_type":"scooter"},{"bike_id":"352897091452345","lat":38.9110183,"lon":-77.04357,"is_reserved":0,"is_disabled":0,"vehicle_type":"scooter"},{"bike_id":"352897091535321","lat":38.9316365,"lon":-77.0405048,"is_reserved":0,"is_disabled":0,"vehicle_type":"scooter"},{"bike_id":"352897091303282","lat":38.9037769,"lon":-77.0528618,"is_reserved":0,"is_disabled":0,"vehicle_type":"scooter"},{"bike_id":"352897091366826","lat":38.8947595,"lon":-77.0025886,"is_reserved":0,"is_disabled":0,"vehicle_type":"scooter"},{"bike_id":"352897091651722","lat":38.9000123,"lon":-77.0318877,"is_reserved":0,"is_disabled":0,"vehicle_type":"scooter"},{"bike_id":"352897091525769","lat":38.905052,"lon":-77.0519781,"is_reserved":0,"is_disabled":0,"vehicle_type":"scooter"},{"bike_id":"352897091433345","lat":38.8799956,"lon":-76.9853885,"is_reserved":0,"is_disabled":0,"vehicle_type":"scooter"},{"bike_id":"352897091345242","lat":38.9140167,"lon":-77.0363183,"is_reserved":0,"is_disabled":0,"vehicle_type":"scooter"},{"bike_id":"352897091472962","lat":38.9044593,"lon":-77.017001,"is_reserved":0,"is_disabled":0,"vehicle_type":"scooter"},{"bike_id":"352897091459126","lat":38.8940615,"lon":-77.0214045,"is_reserved":0,"is_disabled":0,"vehicle_type":"scooter"},{"bike_id":"352897091468085","lat":38.9155367,"lon":-77.0374092,"is_reserved":0,"is_disabled":0,"vehicle_type":"scooter"},{"bike_id":"352897091277247","lat":38.8771199,"lon":-77.0183544,"is_reserved":0,"is_disabled":0,"vehicle_type":"scooter"},{"bike_id":"352897091403561","lat":38.925395,"lon":-77.0326133,"is_reserved":0,"is_disabled":0,"vehicle_type":"scooter"},{"bike_id":"352897091469588","lat":38.9132503,"lon":-77.0518814,"is_reserved":0,"is_disabled":0,"vehicle_type":"scooter"},{"bike_id":"352897091551484","lat":38.9243617,"lon":-77.033635,"is_reserved":0,"is_disabled":0,"vehicle_type":"scooter"},{"bike_id":"352897091347305","lat":38.9211926,"lon":-77.044087,"is_reserved":0,"is_disabled":0,"vehicle_type":"scooter"},{"bike_id":"352897091363542","lat":38.8961752,"lon":-77.0321708,"is_reserved":0,"is_disabled":0,"vehicle_type":"scooter"},{"bike_id":"352897091647621","lat":38.9288479,"lon":-77.0320936,"is_reserved":0,"is_disabled":0,"vehicle_type":"scooter"},{"bike_id":"352897091402985","lat":38.9196413,"lon":-77.0418848,"is_reserved":0,"is_disabled":0,"vehicle_type":"scooter"},{"bike_id":"352897091341803","lat":38.9289235,"lon":-77.0334887,"is_reserved":0,"is_disabled":0,"vehicle_type":"scooter"},{"bike_id":"352897091425622","lat":38.9022617,"lon":-76.9436067,"is_reserved":0,"is_disabled":0,"vehicle_type":"scooter"},{"bike_id":"352897091363583","lat":38.9085383,"lon":-77.0460183,"is_reserved":0,"is_disabled":0,"vehicle_type":"scooter"},{"bike_id":"352897091526080","lat":38.8910267,"lon":-76.952565,"is_reserved":0,"is_disabled":0,"vehicle_type":"scooter"},{"bike_id":"352897091378862","lat":38.8986881,"lon":-76.9767031,"is_reserved":0,"is_disabled":0,"vehicle_type":"scooter"},{"bike_id":"352897091448244","lat":38.9039433,"lon":-77.0533817,"is_reserved":0,"is_disabled":0,"vehicle_type":"scooter"},{"bike_id":"352897091269509","lat":38.9142696,"lon":-77.0450809,"is_reserved":0,"is_disabled":0,"vehicle_type":"scooter"},{"bike_id":"352897091442387","lat":38.920632,"lon":-77.0259454,"is_reserved":0,"is_disabled":0,"vehicle_type":"scooter"},{"bike_id":"352897091458144","lat":38.9164985,"lon":-77.0270322,"is_reserved":0,"is_disabled":0,"vehicle_type":"scooter"},{"bike_id":"352897091276249","lat":38.903847,"lon":-76.9753933,"is_reserved":0,"is_disabled":0,"vehicle_type":"scooter"},{"bike_id":"352897091408289","lat":38.9083562,"lon":-77.043698,"is_reserved":0,"is_disabled":0,"vehicle_type":"scooter"},{"bike_id":"352897091319387","lat":38.9001867,"lon":-77.020147,"is_reserved":0,"is_disabled":0,"vehicle_type":"scooter"},{"bike_id":"352897091529860","lat":38.8766747,"lon":-77.007272,"is_reserved":0,"is_disabled":0,"vehicle_type":"scooter"},{"bike_id":"352897091369721","lat":38.9058617,"lon":-77.008295,"is_reserved":0,"is_disabled":0,"vehicle_type":"scooter"},{"bike_id":"352897091437684","lat":38.9069644,"lon":-77.024019,"is_reserved":0,"is_disabled":0,"vehicle_type":"scooter"},{"bike_id":"352897091443385","lat":38.9031626,"lon":-77.0236817,"is_reserved":0,"is_disabled":0,"vehicle_type":"scooter"},{"bike_id":"352897091354020","lat":38.8961105,"lon":-77.0322136,"is_reserved":0,"is_disabled":0,"vehicle_type":"scooter"},{"bike_id":"352897091487549","lat":38.8937267,"lon":-76.9500017,"is_reserved":0,"is_disabled":0,"vehicle_type":"scooter"},{"bike_id":"352897091471121","lat":38.9069467,"lon":-77.051255,"is_reserved":0,"is_disabled":0,"vehicle_type":"scooter"},{"bike_id":"352897091437585","lat":38.8748644,"lon":-77.0010801,"is_reserved":0,"is_disabled":0,"vehicle_type":"scooter"},{"bike_id":"352897091379688","lat":38.9056347,"lon":-77.0296378,"is_reserved":0,"is_disabled":0,"vehicle_type":"scooter"},{"bike_id":"352897091476260","lat":38.8875248,"lon":-76.9991869,"is_reserved":0,"is_disabled":0,"vehicle_type":"scooter"},{"bike_id":"352897091423841","lat":38.8983049,"lon":-77.0467161,"is_reserved":0,"is_disabled":0,"vehicle_type":"scooter"},{"bike_id":"352897091299241","lat":38.9016233,"lon":-77.0483667,"is_reserved":0,"is_disabled":0,"vehicle_type":"scooter"},{"bike_id":"352897091401326","lat":38.9033798,"lon":-77.0115824,"is_reserved":0,"is_disabled":0,"vehicle_type":"scooter"},{"bike_id":"352897091415268","lat":38.8957377,"lon":-77.0064751,"is_reserved":0,"is_disabled":0,"vehicle_type":"scooter"},{"bike_id":"352897091347461","lat":38.9094797,"lon":-77.0406606,"is_reserved":0,"is_disabled":0,"vehicle_type":"scooter"},{"bike_id":"352897091264625","lat":38.8982567,"lon":-77.04643,"is_reserved":0,"is_disabled":0,"vehicle_type":"scooter"},{"bike_id":"352897091370927","lat":38.9315267,"lon":-77.0215017,"is_reserved":0,"is_disabled":0,"vehicle_type":"scooter"},{"bike_id":"352897091378060","lat":38.9017816,"lon":-77.0260529,"is_reserved":0,"is_disabled":0,"vehicle_type":"scooter"},{"bike_id":"352897091439409","lat":38.9451976,"lon":-77.0724843,"is_reserved":0,"is_disabled":0,"vehicle_type":"scooter"},{"bike_id":"352897091393226","lat":38.8656667,"lon":-76.9892867,"is_reserved":0,"is_disabled":0,"vehicle_type":"scooter"},{"bike_id":"352897091335805","lat":38.9176699,"lon":-77.0356319,"is_reserved":0,"is_disabled":0,"vehicle_type":"scooter"},{"bike_id":"352897091418601","lat":38.9022989,"lon":-77.0434477,"is_reserved":0,"is_disabled":0,"vehicle_type":"scooter"},{"bike_id":"352897091288301","lat":38.9027068,"lon":-77.0188058,"is_reserved":0,"is_disabled":0,"vehicle_type":"scooter"},{"bike_id":"352897091295801","lat":38.91111,"lon":-77.04416,"is_reserved":0,"is_disabled":0,"vehicle_type":"scooter"},{"bike_id":"352897091356769","lat":38.9051621,"lon":-77.0485505,"is_reserved":0,"is_disabled":0,"vehicle_type":"scooter"},{"bike_id":"352897091483167","lat":38.9166349,"lon":-77.0364258,"is_reserved":0,"is_disabled":0,"vehicle_type":"scooter"},{"bike_id":"352897091400146","lat":38.9335282,"lon":-77.0725575,"is_reserved":0,"is_disabled":0,"vehicle_type":"scooter"},{"bike_id":"352897091552029","lat":38.9107494,"lon":-76.9970607,"is_reserved":0,"is_disabled":0,"vehicle_type":"scooter"},{"bike_id":"352897091352669","lat":38.9005739,"lon":-77.0188722,"is_reserved":0,"is_disabled":0,"vehicle_type":"scooter"},{"bike_id":"352897091325988","lat":38.9007781,"lon":-77.0527059,"is_reserved":0,"is_disabled":0,"vehicle_type":"scooter"},{"bike_id":"352897091404007","lat":38.9004567,"lon":-77.0269633,"is_reserved":0,"is_disabled":0,"vehicle_type":"scooter"},{"bike_id":"352897091297609","lat":38.9072478,"lon":-77.0288743,"is_reserved":0,"is_disabled":0,"vehicle_type":"scooter"},{"bike_id":"352897091382062","lat":38.9003233,"lon":-77.0092217,"is_reserved":0,"is_disabled":0,"vehicle_type":"scooter"},{"bike_id":"352897091355225","lat":38.893815,"lon":-76.949975,"is_reserved":0,"is_disabled":0,"vehicle_type":"scooter"},{"bike_id":"352897091270481","lat":38.9119488,"lon":-77.0446041,"is_reserved":0,"is_disabled":0,"vehicle_type":"scooter"},{"bike_id":"352897091280720","lat":38.91578,"lon":-77.045375,"is_reserved":0,"is_disabled":0,"vehicle_type":"scooter"},{"bike_id":"352897091415904","lat":38.8959023,"lon":-77.0277893,"is_reserved":0,"is_disabled":0,"vehicle_type":"scooter"},{"bike_id":"352897091561624","lat":38.91806,"lon":-77.0346017,"is_reserved":0,"is_disabled":0,"vehicle_type":"scooter"},{"bike_id":"352897091297781","lat":38.91673,"lon":-77.036625,"is_reserved":0,"is_disabled":0,"vehicle_type":"scooter"},{"bike_id":"352897091547847","lat":38.9268848,"lon":-77.028393,"is_reserved":0,"is_disabled":0,"vehicle_type":"scooter"},{"bike_id":"352897091339567","lat":38.9095963,"lon":-77.0403956,"is_reserved":0,"is_disabled":0,"vehicle_type":"scooter"},{"bike_id":"352897091433469","lat":38.9247956,"lon":-77.0319296,"is_reserved":0,"is_disabled":0,"vehicle_type":"scooter"},{"bike_id":"352897091535586","lat":38.9096766,"lon":-77.0485794,"is_reserved":0,"is_disabled":0,"vehicle_type":"scooter"},{"bike_id":"352897091327661","lat":38.8952167,"lon":-77.0393767,"is_reserved":0,"is_disabled":0,"vehicle_type":"scooter"},{"bike_id":"352897091470024","lat":38.9039964,"lon":-77.0627422,"is_reserved":0,"is_disabled":0,"vehicle_type":"scooter"},{"bike_id":"352897091487127","lat":38.9017463,"lon":-77.050937,"is_reserved":0,"is_disabled":0,"vehicle_type":"scooter"},{"bike_id":"352897091410301","lat":38.910155,"lon":-77.0343933,"is_reserved":0,"is_disabled":0,"vehicle_type":"scooter"},{"bike_id":"352897091320187","lat":38.905125,"lon":-77.0611133,"is_reserved":0,"is_disabled":0,"vehicle_type":"scooter"},{"bike_id":"352897091643042","lat":38.9267247,"lon":-77.0434685,"is_reserved":0,"is_disabled":0,"vehicle_type":"scooter"},{"bike_id":"352897091284748","lat":38.897515,"lon":-77.018755,"is_reserved":0,"is_disabled":0,"vehicle_type":"scooter"},{"bike_id":"352897091389802","lat":38.9032185,"lon":-77.0118895,"is_reserved":0,"is_disabled":0,"vehicle_type":"scooter"},{"bike_id":"352897091454549","lat":38.8880167,"lon":-77.0025233,"is_reserved":0,"is_disabled":0,"vehicle_type":"scooter"},{"bike_id":"352897091404163","lat":38.8971752,"lon":-76.9948617,"is_reserved":0,"is_disabled":0,"vehicle_type":"scooter"},{"bike_id":"352897091533821","lat":38.8778867,"lon":-77.0058067,"is_reserved":0,"is_disabled":0,"vehicle_type":"scooter"},{"bike_id":"352897091363302","lat":38.8837133,"lon":-76.9955933,"is_reserved":0,"is_disabled":0,"vehicle_type":"scooter"},{"bike_id":"352897091342108","lat":38.9003689,"lon":-77.0200588,"is_reserved":0,"is_disabled":0,"vehicle_type":"scooter"},{"bike_id":"352897091358567","lat":38.8989867,"lon":-77.0514667,"is_reserved":0,"is_disabled":0,"vehicle_type":"scooter"},{"bike_id":"352897091459365","lat":38.9025176,"lon":-77.0395385,"is_reserved":0,"is_disabled":0,"vehicle_type":"scooter"},{"bike_id":"352897091412281","lat":38.9192533,"lon":-77.04871,"is_reserved":0,"is_disabled":0,"vehicle_type":"scooter"},{"bike_id":"352897091427164","lat":38.923425,"lon":-77.0434383,"is_reserved":0,"is_disabled":0,"vehicle_type":"scooter"},{"bike_id":"352897091455066","lat":38.8916642,"lon":-76.9868829,"is_reserved":0,"is_disabled":0,"vehicle_type":"scooter"},{"bike_id":"352897091535941","lat":38.9006099,"lon":-77.0487388,"is_reserved":0,"is_disabled":0,"vehicle_type":"scooter"},{"bike_id":"352897091468788","lat":38.9004284,"lon":-77.0556533,"is_reserved":0,"is_disabled":0,"vehicle_type":"scooter"},{"bike_id":"352897091413545","lat":38.8973835,"lon":-77.0431272,"is_reserved":0,"is_disabled":0,"vehicle_type":"scooter"},{"bike_id":"352897091336944","lat":38.908855,"lon":-77.0434333,"is_reserved":0,"is_disabled":0,"vehicle_type":"scooter"},{"bike_id":"352897091555303","lat":38.9289174,"lon":-77.032834,"is_reserved":0,"is_disabled":0,"vehicle_type":"scooter"},{"bike_id":"352897091357809","lat":38.9227667,"lon":-77.0423949,"is_reserved":0,"is_disabled":0,"vehicle_type":"scooter"},{"bike_id":"352897091636608","lat":38.9037955,"lon":-77.053238,"is_reserved":0,"is_disabled":0,"vehicle_type":"scooter"},{"bike_id":"352897091291941","lat":38.9157583,"lon":-77.0380467,"is_reserved":0,"is_disabled":0,"vehicle_type":"scooter"},{"bike_id":"352897091441769","lat":38.900715,"lon":-77.0021317,"is_reserved":0,"is_disabled":0,"vehicle_type":"scooter"},{"bike_id":"352897091365968","lat":38.913585,"lon":-77.0455967,"is_reserved":0,"is_disabled":0,"vehicle_type":"scooter"},{"bike_id":"352897091455603","lat":38.9193456,"lon":-77.031991,"is_reserved":0,"is_disabled":0,"vehicle_type":"scooter"},{"bike_id":"352897091654627","lat":38.8782417,"lon":-77.0036316,"is_reserved":0,"is_disabled":0,"vehicle_type":"scooter"},{"bike_id":"352897091454069","lat":38.8887175,"lon":-76.9408161,"is_reserved":0,"is_disabled":0,"vehicle_type":"scooter"},{"bike_id":"352897091329469","lat":38.93597,"lon":-77.05861,"is_reserved":0,"is_disabled":0,"vehicle_type":"scooter"},{"bike_id":"352897091313745","lat":38.9042371,"lon":-77.0549567,"is_reserved":0,"is_disabled":0,"vehicle_type":"scooter"},{"bike_id":"352897091467921","lat":38.8990346,"lon":-76.939063,"is_reserved":0,"is_disabled":0,"vehicle_type":"scooter"},{"bike_id":"352897091298524","lat":38.8441813,"lon":-76.9977994,"is_reserved":0,"is_disabled":0,"vehicle_type":"scooter"},{"bike_id":"352897091327968","lat":38.9034951,"lon":-77.0089087,"is_reserved":0,"is_disabled":0,"vehicle_type":"scooter"},{"bike_id":"352897091337744","lat":38.8774267,"lon":-77.0037,"is_reserved":0,"is_disabled":0,"vehicle_type":"scooter"},{"bike_id":"352897091447626","lat":38.88422,"lon":-77.006845,"is_reserved":0,"is_disabled":0,"vehicle_type":"scooter"},{"bike_id":"352897091365323","lat":38.9169834,"lon":-77.0386784,"is_reserved":0,"is_disabled":0,"vehicle_type":"scooter"},{"bike_id":"352897091468184","lat":38.8968664,"lon":-76.9475077,"is_reserved":0,"is_disabled":0,"vehicle_type":"scooter"},{"bike_id":"352897091297245","lat":38.9102397,"lon":-77.0222068,"is_reserved":0,"is_disabled":0,"vehicle_type":"scooter"},{"bike_id":"352897091450000","lat":38.8990367,"lon":-77.0332367,"is_reserved":0,"is_disabled":0,"vehicle_type":"scooter"},{"bike_id":"352897091423783","lat":38.8974703,"lon":-77.0479988,"is_reserved":0,"is_disabled":0,"vehicle_type":"scooter"},{"bike_id":"352897091471923","lat":38.9236026,"lon":-77.0507762,"is_reserved":0,"is_disabled":0,"vehicle_type":"scooter"},{"bike_id":"352897091453343","lat":38.9162663,"lon":-77.0484921,"is_reserved":0,"is_disabled":0,"vehicle_type":"scooter"},{"bike_id":"352897091641905","lat":38.9045365,"lon":-77.0327137,"is_reserved":0,"is_disabled":0,"vehicle_type":"scooter"},{"bike_id":"352897091441868","lat":38.9088073,"lon":-77.064956,"is_reserved":0,"is_disabled":0,"vehicle_type":"scooter"},{"bike_id":"352897091407141","lat":38.8768183,"lon":-77.0001583,"is_reserved":0,"is_disabled":0,"vehicle_type":"scooter"},{"bike_id":"352897091414808","lat":38.9247683,"lon":-77.0392717,"is_reserved":0,"is_disabled":0,"vehicle_type":"scooter"},{"bike_id":"352897091373483","lat":38.8963151,"lon":-77.0448608,"is_reserved":0,"is_disabled":0,"vehicle_type":"scooter"},{"bike_id":"352897091455504","lat":38.9061188,"lon":-77.0629527,"is_reserved":0,"is_disabled":0,"vehicle_type":"scooter"},{"bike_id":"352897091555345","lat":38.90012,"lon":-77.049105,"is_reserved":0,"is_disabled":0,"vehicle_type":"scooter"},{"bike_id":"352897091380140","lat":38.9104515,"lon":-76.9947272,"is_reserved":0,"is_disabled":0,"vehicle_type":"scooter"},{"bike_id":"352897091552383","lat":38.9360618,"lon":-77.0586511,"is_reserved":0,"is_disabled":0,"vehicle_type":"scooter"},{"bike_id":"352897091265127","lat":38.9003682,"lon":-77.0270016,"is_reserved":0,"is_disabled":0,"vehicle_type":"scooter"},{"bike_id":"352897091408446","lat":38.87474,"lon":-77.0006517,"is_reserved":0,"is_disabled":0,"vehicle_type":"scooter"},{"bike_id":"352897091403447","lat":38.87648,"lon":-76.965035,"is_reserved":0,"is_disabled":0,"vehicle_type":"scooter"},{"bike_id":"352897091358765","lat":38.89236,"lon":-77.0261966,"is_reserved":0,"is_disabled":0,"vehicle_type":"scooter"},{"bike_id":"352897091308729","lat":38.9133331,"lon":-77.0149867,"is_reserved":0,"is_disabled":0,"vehicle_type":"scooter"},{"bike_id":"352897091300023","lat":38.9306178,"lon":-77.0381893,"is_reserved":0,"is_disabled":0,"vehicle_type":"scooter"},{"bike_id":"352897091367360","lat":38.90447,"lon":-77.05922,"is_reserved":0,"is_disabled":0,"vehicle_type":"scooter"},{"bike_id":"352897091383706","lat":38.8923181,"lon":-77.0262648,"is_reserved":0,"is_disabled":0,"vehicle_type":"scooter"},{"bike_id":"352897091447360","lat":38.8933597,"lon":-77.0316515,"is_reserved":0,"is_disabled":0,"vehicle_type":"scooter"},{"bike_id":"352897091479587","lat":38.9170651,"lon":-76.9801841,"is_reserved":0,"is_disabled":0,"vehicle_type":"scooter"},{"bike_id":"352897091367980","lat":38.9073417,"lon":-77.0319233,"is_reserved":0,"is_disabled":0,"vehicle_type":"scooter"},{"bike_id":"352897091369705","lat":38.9289042,"lon":-77.0324695,"is_reserved":0,"is_disabled":0,"vehicle_type":"scooter"},{"bike_id":"352897091376544","lat":38.8778899,"lon":-77.0060833,"is_reserved":0,"is_disabled":0,"vehicle_type":"scooter"},{"bike_id":"352897091276025","lat":38.9322339,"lon":-77.0368285,"is_reserved":0,"is_disabled":0,"vehicle_type":"scooter"},{"bike_id":"352897091430986","lat":38.9053532,"lon":-77.0540893,"is_reserved":0,"is_disabled":0,"vehicle_type":"scooter"},{"bike_id":"352897091393861","lat":38.911835,"lon":-77.0107117,"is_reserved":0,"is_disabled":0,"vehicle_type":"scooter"},{"bike_id":"352897091396500","lat":38.9275137,"lon":-77.023707,"is_reserved":0,"is_disabled":0,"vehicle_type":"scooter"},{"bike_id":"352897091455082","lat":38.9238383,"lon":-77.0406033,"is_reserved":0,"is_disabled":0,"vehicle_type":"scooter"},{"bike_id":"352897091479041","lat":38.91684,"lon":-77.02956,"is_reserved":0,"is_disabled":0,"vehicle_type":"scooter"},{"bike_id":"352897091375900","lat":38.9056448,"lon":-77.0130188,"is_reserved":0,"is_disabled":0,"vehicle_type":"scooter"},{"bike_id":"352897091405848","lat":38.9139994,"lon":-77.0363872,"is_reserved":0,"is_disabled":0,"vehicle_type":"scooter"},{"bike_id":"352897091397060","lat":38.8925057,"lon":-77.0262379,"is_reserved":0,"is_disabled":0,"vehicle_type":"scooter"},{"bike_id":"352897091433204","lat":38.909955,"lon":-77.033705,"is_reserved":0,"is_disabled":0,"vehicle_type":"scooter"},{"bike_id":"352897091307267","lat":38.929995,"lon":-77.0327367,"is_reserved":0,"is_disabled":0,"vehicle_type":"scooter"},{"bike_id":"352897091338403","lat":38.8878482,"lon":-76.9335877,"is_reserved":0,"is_disabled":0,"vehicle_type":"scooter"},{"bike_id":"352897091641541","lat":38.9053107,"lon":-77.0028974,"is_reserved":0,"is_disabled":0,"vehicle_type":"scooter"},{"bike_id":"352897091370547","lat":38.9084671,"lon":-76.9995942,"is_reserved":0,"is_disabled":0,"vehicle_type":"scooter"},{"bike_id":"352897091425267","lat":38.88449,"lon":-77.0089783,"is_reserved":0,"is_disabled":0,"vehicle_type":"scooter"},{"bike_id":"352897091318488","lat":38.9081614,"lon":-77.0416549,"is_reserved":0,"is_disabled":0,"vehicle_type":"scooter"},{"bike_id":"352897091330046","lat":38.9307182,"lon":-77.0315776,"is_reserved":0,"is_disabled":0,"vehicle_type":"scooter"},{"bike_id":"352897091423601","lat":38.907835,"lon":-77.0582183,"is_reserved":0,"is_disabled":0,"vehicle_type":"scooter"},{"bike_id":"352897091298680","lat":38.9088017,"lon":-77.0345133,"is_reserved":0,"is_disabled":0,"vehicle_type":"scooter"},{"bike_id":"352897091357643","lat":38.9297717,"lon":-77.034705,"is_reserved":0,"is_disabled":0,"vehicle_type":"scooter"},{"bike_id":"352897091515521","lat":38.9016767,"lon":-77.0510167,"is_reserved":0,"is_disabled":0,"vehicle_type":"scooter"},{"bike_id":"352897091416563","lat":38.9040683,"lon":-77.0530684,"is_reserved":0,"is_disabled":0,"vehicle_type":"scooter"},{"bike_id":"352897091350622","lat":38.8795062,"lon":-77.0170079,"is_reserved":0,"is_disabled":0,"vehicle_type":"scooter"},{"bike_id":"352897091482987","lat":38.915109,"lon":-77.0446084,"is_reserved":0,"is_disabled":0,"vehicle_type":"scooter"},{"bike_id":"352897091643463","lat":38.9209565,"lon":-77.0319768,"is_reserved":0,"is_disabled":0,"vehicle_type":"scooter"},{"bike_id":"352897091655889","lat":38.9032064,"lon":-77.023587,"is_reserved":0,"is_disabled":0,"vehicle_type":"scooter"},{"bike_id":"352897091362569","lat":38.9292424,"lon":-77.0327117,"is_reserved":0,"is_disabled":0,"vehicle_type":"scooter"},{"bike_id":"352897091394588","lat":38.9157019,"lon":-77.0380265,"is_reserved":0,"is_disabled":0,"vehicle_type":"scooter"},{"bike_id":"352897091467889","lat":38.9055217,"lon":-77.0418449,"is_reserved":0,"is_disabled":0,"vehicle_type":"scooter"},{"bike_id":"352897091264740","lat":38.8962374,"lon":-77.0448624,"is_reserved":0,"is_disabled":0,"vehicle_type":"scooter"},{"bike_id":"352897091311145","lat":38.9019342,"lon":-77.0270429,"is_reserved":0,"is_disabled":0,"vehicle_type":"scooter"},{"bike_id":"352897091414121","lat":38.8960075,"lon":-77.0099346,"is_reserved":0,"is_disabled":0,"vehicle_type":"scooter"},{"bike_id":"352897091424948","lat":38.88179,"lon":-77.005975,"is_reserved":0,"is_disabled":0,"vehicle_type":"scooter"},{"bike_id":"352897091279201","lat":38.919404,"lon":-77.031971,"is_reserved":0,"is_disabled":0,"vehicle_type":"scooter"},{"bike_id":"352897091390404","lat":38.9064117,"lon":-77.06113,"is_reserved":0,"is_disabled":0,"vehicle_type":"scooter"},{"bike_id":"352897091638687","lat":38.9067283,"lon":-77.0741611,"is_reserved":0,"is_disabled":0,"vehicle_type":"scooter"},{"bike_id":"352897091446404","lat":38.90965,"lon":-77.04859,"is_reserved":0,"is_disabled":0,"vehicle_type":"scooter"},{"bike_id":"352897091532948","lat":38.9060668,"lon":-77.007919,"is_reserved":0,"is_disabled":0,"vehicle_type":"scooter"},{"bike_id":"352897091643026","lat":38.887711,"lon":-76.9557298,"is_reserved":0,"is_disabled":0,"vehicle_type":"scooter"},{"bike_id":"352897091294507","lat":38.9167783,"lon":-77.0366017,"is_reserved":0,"is_disabled":0,"vehicle_type":"scooter"},{"bike_id":"352897091459522","lat":38.9237306,"lon":-77.0408122,"is_reserved":0,"is_disabled":0,"vehicle_type":"scooter"},{"bike_id":"352897091378482","lat":38.9238133,"lon":-77.0274183,"is_reserved":0,"is_disabled":0,"vehicle_type":"scooter"},{"bike_id":"352897091491004","lat":38.9004723,"lon":-77.0087524,"is_reserved":0,"is_disabled":0,"vehicle_type":"scooter"},{"bike_id":"352897091314065","lat":38.9233583,"lon":-77.0441117,"is_reserved":0,"is_disabled":0,"vehicle_type":"scooter"},{"bike_id":"352897091307309","lat":38.9092032,"lon":-77.0466215,"is_reserved":0,"is_disabled":0,"vehicle_type":"scooter"},{"bike_id":"352897091567001","lat":38.9361582,"lon":-77.0380369,"is_reserved":0,"is_disabled":0,"vehicle_type":"scooter"},{"bike_id":"352897091420946","lat":38.89805,"lon":-77.0167267,"is_reserved":0,"is_disabled":0,"vehicle_type":"scooter"},{"bike_id":"352897091642085","lat":38.9031884,"lon":-77.025515,"is_reserved":0,"is_disabled":0,"vehicle_type":"scooter"},{"bike_id":"352897091448707","lat":38.8753567,"lon":-77.2346667,"is_reserved":0,"is_disabled":0,"vehicle_type":"scooter"},{"bike_id":"352897091455009","lat":38.896023,"lon":-77.0219474,"is_reserved":0,"is_disabled":0,"vehicle_type":"scooter"},{"bike_id":"352897091424708","lat":38.918055,"lon":-77.0315867,"is_reserved":0,"is_disabled":0,"vehicle_type":"scooter"},{"bike_id":"352897091329907","lat":38.9132362,"lon":-77.015101,"is_reserved":0,"is_disabled":0,"vehicle_type":"scooter"},{"bike_id":"352897091449929","lat":38.9086091,"lon":-77.0561962,"is_reserved":0,"is_disabled":0,"vehicle_type":"scooter"},{"bike_id":"352897091531809","lat":38.9020567,"lon":-77.0539967,"is_reserved":0,"is_disabled":0,"vehicle_type":"scooter"},{"bike_id":"352897091640329","lat":38.9155067,"lon":-77.041685,"is_reserved":0,"is_disabled":0,"vehicle_type":"scooter"},{"bike_id":"352897091327323","lat":38.876955,"lon":-77.0060467,"is_reserved":0,"is_disabled":0,"vehicle_type":"scooter"},{"bike_id":"352897091300668","lat":38.90133,"lon":-77.0168183,"is_reserved":0,"is_disabled":0,"vehicle_type":"scooter"},{"bike_id":"352897091278567","lat":38.9004613,"lon":-77.0087786,"is_reserved":0,"is_disabled":0,"vehicle_type":"scooter"},{"bike_id":"352897091455561","lat":38.8974503,"lon":-77.0212133,"is_reserved":0,"is_disabled":0,"vehicle_type":"scooter"},{"bike_id":"352897091436181","lat":38.9048183,"lon":-77.019985,"is_reserved":0,"is_disabled":0,"vehicle_type":"scooter"},{"bike_id":"352897091402084","lat":38.8984567,"lon":-77.0319883,"is_reserved":0,"is_disabled":0,"vehicle_type":"scooter"},{"bike_id":"352897091384001","lat":38.8802124,"lon":-77.0167959,"is_reserved":0,"is_disabled":0,"vehicle_type":"scooter"},{"bike_id":"352897091460363","lat":38.9169217,"lon":-77.03867,"is_reserved":0,"is_disabled":0,"vehicle_type":"scooter"},{"bike_id":"352897091315963","lat":38.9000917,"lon":-77.0412867,"is_reserved":0,"is_disabled":0,"vehicle_type":"scooter"},{"bike_id":"352897091639644","lat":38.8961717,"lon":-77.0447767,"is_reserved":0,"is_disabled":0,"vehicle_type":"scooter"},{"bike_id":"352897091402605","lat":38.915795,"lon":-77.0500067,"is_reserved":0,"is_disabled":0,"vehicle_type":"scooter"},{"bike_id":"352897091278302","lat":38.89772,"lon":-77.0512467,"is_reserved":0,"is_disabled":0,"vehicle_type":"scooter"},{"bike_id":"352897091404320","lat":38.9039883,"lon":-77.01638,"is_reserved":0,"is_disabled":0,"vehicle_type":"scooter"},{"bike_id":"352897091305840","lat":38.9037217,"lon":-77.0175683,"is_reserved":0,"is_disabled":0,"vehicle_type":"scooter"},{"bike_id":"352897091539620","lat":38.898275,"lon":-77.0465183,"is_reserved":0,"is_disabled":0,"vehicle_type":"scooter"},{"bike_id":"352897091391220","lat":38.8924217,"lon":-77.0153733,"is_reserved":0,"is_disabled":0,"vehicle_type":"scooter"},{"bike_id":"352897091438229","lat":38.914635,"lon":-77.0670733,"is_reserved":0,"is_disabled":0,"vehicle_type":"scooter"},{"bike_id":"352897091648520","lat":38.91328,"lon":-77.0150233,"is_reserved":0,"is_disabled":0,"vehicle_type":"scooter"},{"bike_id":"352897091319866","lat":38.8957043,"lon":-77.0229954,"is_reserved":0,"is_disabled":0,"vehicle_type":"scooter"},{"bike_id":"352897091360043","lat":38.9077618,"lon":-77.0580779,"is_reserved":0,"is_disabled":0,"vehicle_type":"scooter"},{"bike_id":"352897091642200","lat":38.8810667,"lon":-77.0265183,"is_reserved":0,"is_disabled":0,"vehicle_type":"scooter"},{"bike_id":"352897091376486","lat":38.8731429,"lon":-77.0108398,"is_reserved":0,"is_disabled":0,"vehicle_type":"scooter"},{"bike_id":"352897091490980","lat":38.9193454,"lon":-77.0322032,"is_reserved":0,"is_disabled":0,"vehicle_type":"scooter"},{"bike_id":"352897091366966","lat":38.9056083,"lon":-77.0295783,"is_reserved":0,"is_disabled":0,"vehicle_type":"scooter"},{"bike_id":"352897091375629","lat":38.907347,"lon":-77.0513832,"is_reserved":0,"is_disabled":0,"vehicle_type":"scooter"},{"bike_id":"352897091397482","lat":38.905252,"lon":-77.0612316,"is_reserved":0,"is_disabled":0,"vehicle_type":"scooter"},{"bike_id":"352897091570047","lat":38.9012073,"lon":-77.0523034,"is_reserved":0,"is_disabled":0,"vehicle_type":"scooter"},{"bike_id":"352897091335607","lat":38.9068597,"lon":-77.0361096,"is_reserved":0,"is_disabled":0,"vehicle_type":"scooter"},{"bike_id":"352897091567068","lat":38.9203499,"lon":-77.0419723,"is_reserved":0,"is_disabled":0,"vehicle_type":"scooter"},{"bike_id":"352897091298706","lat":38.8947733,"lon":-77.022725,"is_reserved":0,"is_disabled":0,"vehicle_type":"scooter"},{"bike_id":"352897091463144","lat":38.90068,"lon":-77.05032,"is_reserved":0,"is_disabled":0,"vehicle_type":"scooter"},{"bike_id":"352897091294846","lat":38.9096617,"lon":-77.0345633,"is_reserved":0,"is_disabled":0,"vehicle_type":"scooter"},{"bike_id":"352897091442023","lat":38.9003297,"lon":-77.0110799,"is_reserved":0,"is_disabled":0,"vehicle_type":"scooter"},{"bike_id":"352897091318223","lat":38.9006433,"lon":-77.0486983,"is_reserved":0,"is_disabled":0,"vehicle_type":"scooter"},{"bike_id":"352897091365083","lat":38.9308533,"lon":-77.0316109,"is_reserved":0,"is_disabled":0,"vehicle_type":"scooter"},{"bike_id":"352897091463789","lat":38.905935,"lon":-77.007635,"is_reserved":0,"is_disabled":0,"vehicle_type":"scooter"},{"bike_id":"352897091420524","lat":38.9058132,"lon":-77.0088772,"is_reserved":0,"is_disabled":0,"vehicle_type":"scooter"},{"bike_id":"352897091296940","lat":38.9102807,"lon":-77.0647064,"is_reserved":0,"is_disabled":0,"vehicle_type":"scooter"},{"bike_id":"352897091407984","lat":38.9060677,"lon":-77.0643854,"is_reserved":0,"is_disabled":0,"vehicle_type":"scooter"},{"bike_id":"352897091409964","lat":38.910209,"lon":-77.034349,"is_reserved":0,"is_disabled":0,"vehicle_type":"scooter"},{"bike_id":"352897091369622","lat":38.9110017,"lon":-77.003405,"is_reserved":0,"is_disabled":0,"vehicle_type":"scooter"},{"bike_id":"352897091368202","lat":38.8940667,"lon":-77.0218517,"is_reserved":0,"is_disabled":0,"vehicle_type":"scooter"},{"bike_id":"352897091403520","lat":38.899318,"lon":-77.0322635,"is_reserved":0,"is_disabled":0,"vehicle_type":"scooter"},{"bike_id":"352897091344328","lat":38.9271928,"lon":-77.0354896,"is_reserved":0,"is_disabled":0,"vehicle_type":"scooter"},{"bike_id":"352897091359227","lat":38.8977417,"lon":-77.0320467,"is_reserved":0,"is_disabled":0,"vehicle_type":"scooter"},{"bike_id":"352897091550601","lat":38.9062514,"lon":-77.0415869,"is_reserved":0,"is_disabled":0,"vehicle_type":"scooter"},{"bike_id":"352897091266026","lat":38.8919617,"lon":-77.0301667,"is_reserved":0,"is_disabled":0,"vehicle_type":"scooter"},{"bike_id":"352897091384142","lat":38.9248867,"lon":-77.0393717,"is_reserved":0,"is_disabled":0,"vehicle_type":"scooter"},{"bike_id":"352897091395601","lat":38.9004567,"lon":-77.0121567,"is_reserved":0,"is_disabled":0,"vehicle_type":"scooter"},{"bike_id":"352897091434269","lat":38.9135321,"lon":-77.0345229,"is_reserved":0,"is_disabled":0,"vehicle_type":"scooter"},{"bike_id":"352897091564743","lat":38.9331837,"lon":-77.0304766,"is_reserved":0,"is_disabled":0,"vehicle_type":"scooter"},{"bike_id":"352897091476104","lat":38.90236,"lon":-77.0175634,"is_reserved":0,"is_disabled":0,"vehicle_type":"scooter"},{"bike_id":"352897091634827","lat":38.9065732,"lon":-77.0417033,"is_reserved":0,"is_disabled":0,"vehicle_type":"scooter"},{"bike_id":"352897091478944","lat":38.9308148,"lon":-77.0381061,"is_reserved":0,"is_disabled":0,"vehicle_type":"scooter"},{"bike_id":"352897091317407","lat":38.9150132,"lon":-77.0383165,"is_reserved":0,"is_disabled":0,"vehicle_type":"scooter"},{"bike_id":"352897091648009","lat":38.9335631,"lon":-77.0572616,"is_reserved":0,"is_disabled":0,"vehicle_type":"scooter"},{"bike_id":"352897091316425","lat":38.9013559,"lon":-77.0397877,"is_reserved":0,"is_disabled":0,"vehicle_type":"scooter"},{"bike_id":"352897091321128","lat":38.876575,"lon":-77.0073217,"is_reserved":0,"is_disabled":0,"vehicle_type":"scooter"},{"bike_id":"352897091648082","lat":38.9046717,"lon":-77.0074117,"is_reserved":0,"is_disabled":0,"vehicle_type":"scooter"},{"lat":38.9106485,"lon":-77.0035049,"is_reserved":0,"is_disabled":0,"vehicle_type":"scooter"},{"bike_id":"352897091376809","lat":38.874903,"lon":-77.0005252,"is_reserved":0,"is_disabled":0,"vehicle_type":"scooter"},{"bike_id":"352897091293848","lat":38.9168133,"lon":-77.0297517,"is_reserved":0,"is_disabled":0,"vehicle_type":"scooter"},{"bike_id":"352897091448467","lat":38.918731,"lon":-77.0430971,"is_reserved":0,"is_disabled":0,"vehicle_type":"scooter"},{"bike_id":"352897091575947","lat":38.8766008,"lon":-77.0042567,"is_reserved":0,"is_disabled":0,"vehicle_type":"scooter"},{"bike_id":"352897091402720","lat":38.8837685,"lon":-77.0188972,"is_reserved":0,"is_disabled":0,"vehicle_type":"scooter"},{"bike_id":"352897091546948","lat":38.89682,"lon":-76.947685,"is_reserved":0,"is_disabled":0,"vehicle_type":"scooter"},{"bike_id":"352897091477607","lat":38.8952233,"lon":-77.028285,"is_reserved":0,"is_disabled":0,"vehicle_type":"scooter"},{"bike_id":"352897091477326","lat":38.90566,"lon":-77.0221583,"is_reserved":0,"is_disabled":0,"vehicle_type":"scooter"},{"bike_id":"352897091351349","lat":38.927365,"lon":-77.0061017,"is_reserved":0,"is_disabled":0,"vehicle_type":"scooter"},{"bike_id":"352897091416449","lat":38.8961883,"lon":-77.0477283,"is_reserved":0,"is_disabled":0,"vehicle_type":"scooter"},{"bike_id":"352897091561400","lat":38.9123046,"lon":-77.0137888,"is_reserved":0,"is_disabled":0,"vehicle_type":"scooter"},{"bike_id":"352897091416605","lat":38.900535,"lon":-77.0005867,"is_reserved":0,"is_disabled":0,"vehicle_type":"scooter"},{"bike_id":"352897091658784","lat":38.90534,"lon":-77.058045,"is_reserved":0,"is_disabled":0,"vehicle_type":"scooter"},{"bike_id":"352897091365802","lat":38.8984351,"lon":-77.0073797,"is_reserved":0,"is_disabled":0,"vehicle_type":"scooter"},{"bike_id":"352897091489446","lat":38.9125036,"lon":-77.0319134,"is_reserved":0,"is_disabled":0,"vehicle_type":"scooter"},{"bike_id":"352897091423403","lat":38.8963227,"lon":-77.0501575,"is_reserved":0,"is_disabled":0,"vehicle_type":"scooter"},{"bike_id":"352897091351463","lat":38.9182312,"lon":-77.0345262,"is_reserved":0,"is_disabled":0,"vehicle_type":"scooter"},{"bike_id":"352897091288640","lat":38.9162883,"lon":-77.0321483,"is_reserved":0,"is_disabled":0,"vehicle_type":"scooter"},{"bike_id":"352897091469885","lat":38.9169233,"lon":-77.0346883,"is_reserved":0,"is_disabled":0,"vehicle_type":"scooter"},{"bike_id":"352897091479967","lat":38.9004767,"lon":-77.0021269,"is_reserved":0,"is_disabled":0,"vehicle_type":"scooter"},{"bike_id":"352897091429921","lat":38.8796281,"lon":-77.0053143,"is_reserved":0,"is_disabled":0,"vehicle_type":"scooter"},{"bike_id":"352897091343429","lat":38.9150847,"lon":-77.0465465,"is_reserved":0,"is_disabled":0,"vehicle_type":"scooter"},{"bike_id":"352897091568207","lat":38.9024017,"lon":-77.0163382,"is_reserved":0,"is_disabled":0,"vehicle_type":"scooter"},{"bike_id":"352897091469125","lat":38.91193,"lon":-77.0425023,"is_reserved":0,"is_disabled":0,"vehicle_type":"scooter"},{"bike_id":"352897091414444","lat":38.9234818,"lon":-77.0433729,"is_reserved":0,"is_disabled":0,"vehicle_type":"scooter"},{"bike_id":"352897091525926","lat":38.8973216,"lon":-77.0034744,"is_reserved":0,"is_disabled":0,"vehicle_type":"scooter"},{"bike_id":"352897091317944","lat":38.8657533,"lon":-76.9893417,"is_reserved":0,"is_disabled":0,"vehicle_type":"scooter"},{"bike_id":"352897091446784","lat":38.901745,"lon":-77.0510267,"is_reserved":0,"is_disabled":0,"vehicle_type":"scooter"},{"bike_id":"352897091263908","lat":38.9281048,"lon":-77.0323394,"is_reserved":0,"is_disabled":0,"vehicle_type":"scooter"},{"bike_id":"352897091382781","lat":38.9324433,"lon":-77.0308667,"is_reserved":0,"is_disabled":0,"vehicle_type":"scooter"},{"bike_id":"352897091387285","lat":38.9248065,"lon":-77.0391592,"is_reserved":0,"is_disabled":0,"vehicle_type":"scooter"},{"bike_id":"352897091407422","lat":38.9496964,"lon":-77.0670018,"is_reserved":0,"is_disabled":0,"vehicle_type":"scooter"},{"bike_id":"352897091434343","lat":38.9243217,"lon":-77.0401617,"is_reserved":0,"is_disabled":0,"vehicle_type":"scooter"},{"bike_id":"352897091311160","lat":38.9088068,"lon":-77.0433334,"is_reserved":0,"is_disabled":0,"vehicle_type":"scooter"},{"bike_id":"352897091379464","lat":38.8971717,"lon":-77.0434617,"is_reserved":0,"is_disabled":0,"vehicle_type":"scooter"},{"bike_id":"352897091412000","lat":38.9069088,"lon":-77.0269297,"is_reserved":0,"is_disabled":0,"vehicle_type":"scooter"},{"bike_id":"352897091270085","lat":38.8973824,"lon":-76.9471958,"is_reserved":0,"is_disabled":0,"vehicle_type":"scooter"},{"bike_id":"352897091567829","lat":38.9142183,"lon":-77.0452015,"is_reserved":0,"is_disabled":0,"vehicle_type":"scooter"},{"bike_id":"352897091279524","lat":38.9169227,"lon":-77.0411744,"is_reserved":0,"is_disabled":0,"vehicle_type":"scooter"},{"bike_id":"352897091299506","lat":38.9239683,"lon":-77.0389533,"is_reserved":0,"is_disabled":0,"vehicle_type":"scooter"},{"bike_id":"352897091303746","lat":38.918864,"lon":-77.0415318,"is_reserved":0,"is_disabled":0,"vehicle_type":"scooter"},{"bike_id":"352897091364763","lat":38.9061867,"lon":-77.0435199,"is_reserved":0,"is_disabled":0,"vehicle_type":"scooter"},{"bike_id":"352897091449788","lat":38.9216545,"lon":-77.0423734,"is_reserved":0,"is_disabled":0,"vehicle_type":"scooter"},{"bike_id":"352897091263502","lat":38.9059829,"lon":-77.0650836,"is_reserved":0,"is_disabled":0,"vehicle_type":"scooter"},{"bike_id":"352897091563869","lat":38.89837,"lon":-77.0436417,"is_reserved":0,"is_disabled":0,"vehicle_type":"scooter"},{"bike_id":"352897091488224","lat":38.9010324,"lon":-77.0200594,"is_reserved":0,"is_disabled":0,"vehicle_type":"scooter"},{"bike_id":"352897091345903","lat":38.9002956,"lon":-77.0006599,"is_reserved":0,"is_disabled":0,"vehicle_type":"scooter"},{"bike_id":"352897091449721","lat":38.9172209,"lon":-77.0297028,"is_reserved":0,"is_disabled":0,"vehicle_type":"scooter"},{"bike_id":"352897091488109","lat":38.8765926,"lon":-77.0042008,"is_reserved":0,"is_disabled":0,"vehicle_type":"scooter"},{"bike_id":"352897091403405","lat":38.918317,"lon":-77.0390098,"is_reserved":0,"is_disabled":0,"vehicle_type":"scooter"},{"bike_id":"352897091447006","lat":38.8821083,"lon":-77.0193433,"is_reserved":0,"is_disabled":0,"vehicle_type":"scooter"},{"bike_id":"352897091437064","lat":38.9287917,"lon":-77.0334183,"is_reserved":0,"is_disabled":0,"vehicle_type":"scooter"},{"bike_id":"352897091449663","lat":38.9224588,"lon":-77.0254017,"is_reserved":0,"is_disabled":0,"vehicle_type":"scooter"},{"bike_id":"352897091416340","lat":38.894475,"lon":-77.0500967,"is_reserved":0,"is_disabled":0,"vehicle_type":"scooter"},{"bike_id":"352897091428543","lat":38.9111167,"lon":-77.0450233,"is_reserved":0,"is_disabled":0,"vehicle_type":"scooter"},{"bike_id":"352897091348626","lat":38.9231863,"lon":-77.0422339,"is_reserved":0,"is_disabled":0,"vehicle_type":"scooter"},{"bike_id":"352897091536824","lat":38.9001189,"lon":-77.0521612,"is_reserved":0,"is_disabled":0,"vehicle_type":"scooter"},{"bike_id":"352897091471527","lat":38.919105,"lon":-77.0706967,"is_reserved":0,"is_disabled":0,"vehicle_type":"scooter"},{"bike_id":"352897091425747","lat":38.9068833,"lon":-77.0619192,"is_reserved":0,"is_disabled":0,"vehicle_type":"scooter"},{"bike_id":"352897091446560","lat":38.9024304,"lon":-77.0396771,"is_reserved":0,"is_disabled":0,"vehicle_type":"scooter"},{"bike_id":"352897091370265","lat":38.892335,"lon":-77.026225,"is_reserved":0,"is_disabled":0,"vehicle_type":"scooter"},{"bike_id":"352897091352404","lat":38.9017533,"lon":-77.0248583,"is_reserved":0,"is_disabled":0,"vehicle_type":"scooter"},{"bike_id":"352897091565146","lat":38.9080467,"lon":-77.0296383,"is_reserved":0,"is_disabled":0,"vehicle_type":"scooter"},{"bike_id":"352897091282122","lat":38.9096533,"lon":-77.0319383,"is_reserved":0,"is_disabled":0,"vehicle_type":"scooter"},{"bike_id":"352897091271802","lat":38.923845,"lon":-77.0411583,"is_reserved":0,"is_disabled":0,"vehicle_type":"scooter"},{"bike_id":"352897091411101","lat":38.8776121,"lon":-77.0073715,"is_reserved":0,"is_disabled":0,"vehicle_type":"scooter"},{"bike_id":"352897091454929","lat":38.896915,"lon":-77.044855,"is_reserved":0,"is_disabled":0,"vehicle_type":"scooter"},{"bike_id":"352897091640105","lat":38.9247467,"lon":-77.0522633,"is_reserved":0,"is_disabled":0,"vehicle_type":"scooter"},{"bike_id":"352897091357924","lat":38.903715,"lon":-77.0501433,"is_reserved":0,"is_disabled":0,"vehicle_type":"scooter"},{"bike_id":"352897091472582","lat":38.8769652,"lon":-77.0185721,"is_reserved":0,"is_disabled":0,"vehicle_type":"scooter"},{"bike_id":"352897091400047","lat":38.9080817,"lon":-77.02821,"is_reserved":0,"is_disabled":0,"vehicle_type":"scooter"},{"bike_id":"352897091344385","lat":38.91487,"lon":-77.0323367,"is_reserved":0,"is_disabled":0,"vehicle_type":"scooter"},{"bike_id":"352897091362643","lat":38.9126126,"lon":-77.0373777,"is_reserved":0,"is_disabled":0,"vehicle_type":"scooter"},{"bike_id":"352897091516289","lat":38.9056536,"lon":-77.0053139,"is_reserved":0,"is_disabled":0,"vehicle_type":"scooter"},{"bike_id":"352897091284201","lat":38.9087385,"lon":-77.0345247,"is_reserved":0,"is_disabled":0,"vehicle_type":"scooter"},{"bike_id":"352897091292469","lat":38.934293,"lon":-77.0399333,"is_reserved":0,"is_disabled":0,"vehicle_type":"scooter"},{"bike_id":"352897091303183","lat":38.8973755,"lon":-76.947173,"is_reserved":0,"is_disabled":0,"vehicle_type":"scooter"},{"bike_id":"352897091477821","lat":38.8987383,"lon":-76.9769752,"is_reserved":0,"is_disabled":0,"vehicle_type":"scooter"},{"bike_id":"352897091523343","lat":38.9103111,"lon":-77.0386686,"is_reserved":0,"is_disabled":0,"vehicle_type":"scooter"},{"bike_id":"352897091298540","lat":38.899175,"lon":-77.016335,"is_reserved":0,"is_disabled":0,"vehicle_type":"scooter"},{"bike_id":"352897091338262","lat":38.8831965,"lon":-76.961172,"is_reserved":0,"is_disabled":0,"vehicle_type":"scooter"},{"bike_id":"352897091430002","lat":38.91499,"lon":-77.0674583,"is_reserved":0,"is_disabled":0,"vehicle_type":"scooter"},{"bike_id":"352897091561806","lat":38.9232305,"lon":-77.0432299,"is_reserved":0,"is_disabled":0,"vehicle_type":"scooter"},{"bike_id":"352897091318645","lat":38.9013095,"lon":-76.9465519,"is_reserved":0,"is_disabled":0,"vehicle_type":"scooter"},{"bike_id":"352897091419807","lat":38.9159917,"lon":-77.0321567,"is_reserved":0,"is_disabled":0,"vehicle_type":"scooter"},{"bike_id":"352897091401201","lat":38.9243482,"lon":-77.0518733,"is_reserved":0,"is_disabled":0,"vehicle_type":"scooter"},{"bike_id":"352897091635964","lat":38.9036128,"lon":-77.0612736,"is_reserved":0,"is_disabled":0,"vehicle_type":"scooter"},{"bike_id":"352897091450828","lat":38.9187434,"lon":-77.0361354,"is_reserved":0,"is_disabled":0,"vehicle_type":"scooter"},{"bike_id":"352897091304124","lat":38.8792913,"lon":-77.0143837,"is_reserved":0,"is_disabled":0,"vehicle_type":"scooter"},{"bike_id":"352897091562689","lat":38.9243917,"lon":-77.040245,"is_reserved":0,"is_disabled":0,"vehicle_type":"scooter"},{"bike_id":"352897091400880","lat":38.8795568,"lon":-77.0053167,"is_reserved":0,"is_disabled":0,"vehicle_type":"scooter"},{"bike_id":"352897091323447","lat":38.907345,"lon":-77.0091333,"is_reserved":0,"is_disabled":0,"vehicle_type":"scooter"},{"bike_id":"352897091438922","lat":38.9000817,"lon":-77.0163833,"is_reserved":0,"is_disabled":0,"vehicle_type":"scooter"},{"bike_id":"352897091527567","lat":38.9335982,"lon":-77.0725483,"is_reserved":0,"is_disabled":0,"vehicle_type":"scooter"},{"bike_id":"352897091446800","lat":38.9036761,"lon":-77.0179516,"is_reserved":0,"is_disabled":0,"vehicle_type":"scooter"},{"bike_id":"352897091517006","lat":38.9061969,"lon":-77.0059865,"is_reserved":0,"is_disabled":0,"vehicle_type":"scooter"},{"bike_id":"352897091322787","lat":38.9164183,"lon":-77.0318878,"is_reserved":0,"is_disabled":0,"vehicle_type":"scooter"},{"bike_id":"352897091376304","lat":38.8905333,"lon":-76.9379917,"is_reserved":0,"is_disabled":0,"vehicle_type":"scooter"},{"bike_id":"352897091379506","lat":38.9017296,"lon":-77.0260003,"is_reserved":0,"is_disabled":0,"vehicle_type":"scooter"},{"bike_id":"352897091441702","lat":38.9376783,"lon":-77.0326533,"is_reserved":0,"is_disabled":0,"vehicle_type":"scooter"},{"bike_id":"352897091452121","lat":38.9286665,"lon":-77.0334919,"is_reserved":0,"is_disabled":0,"vehicle_type":"scooter"},{"bike_id":"352897091374580","lat":38.9037867,"lon":-77.0401717,"is_reserved":0,"is_disabled":0,"vehicle_type":"scooter"},{"bike_id":"352897091433501","lat":38.9020033,"lon":-77.032145,"is_reserved":0,"is_disabled":0,"vehicle_type":"scooter"},{"bike_id":"352897091473341","lat":38.8779266,"lon":-77.0198397,"is_reserved":0,"is_disabled":0,"vehicle_type":"scooter"},{"bike_id":"352897091317688","lat":38.899695,"lon":-77.0206583,"is_reserved":0,"is_disabled":0,"vehicle_type":"scooter"},{"bike_id":"352897091460165","lat":38.9233167,"lon":-77.0564067,"is_reserved":0,"is_disabled":0,"vehicle_type":"scooter"},{"bike_id":"352897091365141","lat":38.9204222,"lon":-77.0420003,"is_reserved":0,"is_disabled":0,"vehicle_type":"scooter"},{"bike_id":"352897091332646","lat":38.9163027,"lon":-76.9830783,"is_reserved":0,"is_disabled":0,"vehicle_type":"scooter"},{"bike_id":"352897091437320","lat":38.9063441,"lon":-77.0413916,"is_reserved":0,"is_disabled":0,"vehicle_type":"scooter"},{"bike_id":"352897091004187","lat":38.8861367,"lon":-77.0075317,"is_reserved":0,"is_disabled":0,"vehicle_type":"scooter"},{"bike_id":"352897091337520","lat":38.8706667,"lon":-77.0137879,"is_reserved":0,"is_disabled":0,"vehicle_type":"scooter"},{"bike_id":"352897091471485","lat":38.8995426,"lon":-77.0483194,"is_reserved":0,"is_disabled":0,"vehicle_type":"scooter"},{"bike_id":"352897091493182","lat":38.9315305,"lon":-77.038575,"is_reserved":0,"is_disabled":0,"vehicle_type":"scooter"},{"bike_id":"352897091393721","lat":38.8832279,"lon":-77.2285511,"is_reserved":0,"is_disabled":0,"vehicle_type":"scooter"},{"bike_id":"352897091432024","lat":38.9150667,"lon":-77.068645,"is_reserved":0,"is_disabled":0,"vehicle_type":"scooter"},{"bike_id":"352897091263320","lat":38.9027118,"lon":-77.0630474,"is_reserved":0,"is_disabled":0,"vehicle_type":"scooter"},{"bike_id":"352897091317027","lat":38.9056717,"lon":-77.0628686,"is_reserved":0,"is_disabled":0,"vehicle_type":"scooter"},{"bike_id":"352897091347420","lat":38.9016537,"lon":-77.0258356,"is_reserved":0,"is_disabled":0,"vehicle_type":"scooter"},{"bike_id":"352897091484025","lat":38.9060415,"lon":-77.0651984,"is_reserved":0,"is_disabled":0,"vehicle_type":"scooter"},{"bike_id":"352897091394745","lat":38.92333,"lon":-77.05126,"is_reserved":0,"is_disabled":0,"vehicle_type":"scooter"},{"bike_id":"352897091419328","lat":38.9109798,"lon":-76.9849903,"is_reserved":0,"is_disabled":0,"vehicle_type":"scooter"},{"bike_id":"352897091442825","lat":38.8784751,"lon":-76.9841453,"is_reserved":0,"is_disabled":0,"vehicle_type":"scooter"},{"bike_id":"352897091408206","lat":38.884157,"lon":-76.97453,"is_reserved":0,"is_disabled":0,"vehicle_type":"scooter"}]}